texutils/__init__.py
texutils/texutils.py
texutils/utils.py
texutils-0.3.0.dist-info/METADATA
texutils-0.3.0.dist-info/WHEEL
texutils-0.3.0.dist-info/RECORD
